tests/utils/__init__.py
tests/utils/cache.py
tests/utils/database.py
tests/utils/dataset.py
ydata/_aiservicetokens.cp312-win32.pyd
ydata/_backoffice.cp312-win32.pyd
ydata/_licensing.cp312-win32.pyd
ydata/__models/__init__.py
ydata/__models/__init__.pyi
ydata/__models/_cartmodel/__init__.py
ydata/__models/_cartmodel/__init__.pyi
ydata/__models/_cartmodel/_common.py
ydata/__models/_cartmodel/_common.pyi
ydata/__models/_cartmodel/_preprocess.py
ydata/__models/_cartmodel/_preprocess.pyi
ydata/__models/_cartmodel/_sequential.py
ydata/__models/_cartmodel/_sequential.pyi
ydata/__models/_cartmodel/_tabular.py
ydata/__models/_cartmodel/_tabular.pyi
ydata/__models/_cartmodel/_utils.py
ydata/__models/_cartmodel/_utils.pyi
ydata/__models/_cartmodel/maps.py
ydata/__models/_cartmodel/maps.pyi
ydata/__models/_cartmodel/_methods/__init__.py
ydata/__models/_cartmodel/_methods/__init__.pyi
ydata/__models/_cartmodel/_methods/base.py
ydata/__models/_cartmodel/_methods/base.pyi
ydata/__models/_cartmodel/_methods/cart.py
ydata/__models/_cartmodel/_methods/cart.pyi
ydata/__models/_cartmodel/_methods/empty.py
ydata/__models/_cartmodel/_methods/empty.pyi
ydata/__models/_cartmodel/_methods/norm.py
ydata/__models/_cartmodel/_methods/norm.pyi
ydata/__models/_cartmodel/_methods/normrank.py
ydata/__models/_cartmodel/_methods/normrank.pyi
ydata/__models/_cartmodel/_methods/perturb.py
ydata/__models/_cartmodel/_methods/perturb.pyi
ydata/__models/_cartmodel/_methods/polyreg.py
ydata/__models/_cartmodel/_methods/polyreg.pyi
ydata/__models/_cartmodel/_methods/sample.py
ydata/__models/_cartmodel/_methods/sample.pyi
ydata/__models/_cartmodel/_methods/utils.py
ydata/__models/_cartmodel/_methods/utils.pyi
ydata/__models/_cartmodel/_methods/xgboost.py
ydata/__models/_cartmodel/_methods/xgboost.pyi
ydata/__models/_gmm/__init__.py
ydata/__models/_gmm/__init__.pyi
ydata/__models/_gmm/_model.py
ydata/__models/_gmm/_model.pyi
ydata/__serializer/__init__.py
ydata/__serializer/__init__.pyi
ydata_sdk-3.0.12.dist-info/licenses/LICENSE.md
ydata_sdk-3.0.12.dist-info/METADATA
ydata_sdk-3.0.12.dist-info/WHEEL
ydata_sdk-3.0.12.dist-info/top_level.txt
ydata_sdk-3.0.12.dist-info/RECORD
