Metadata-Version: 2.4
Name: ydata-sdk
Version: 3.0.12
Summary: YData allows to use the *Data-Centric* tools from the YData ecosystem to accelerate AI development
Author-email: YData <developers@ydata.ai>
License: # YData Package 
Project-URL: Homepage, https://ydata.ai
Keywords: data,science,ydata,datascience,ydataai
Classifier: Development Status :: 5 - Production/Stable
Classifier: Intended Audience :: Developers
Classifier: Intended Audience :: Education
Classifier: Intended Audience :: End Users/Desktop
Classifier: Intended Audience :: Financial and Insurance Industry
Classifier: Intended Audience :: Healthcare Industry
Classifier: Intended Audience :: Science/Research
Classifier: Intended Audience :: Telecommunications Industry
Classifier: Operating System :: POSIX :: Linux
Classifier: Operating System :: MacOS
Classifier: Operating System :: Microsoft :: Windows
Classifier: Programming Language :: Python :: 3 :: Only
Classifier: Programming Language :: Python :: Implementation
Classifier: Topic :: Scientific/Engineering :: Artificial Intelligence
Classifier: Topic :: Software Development
Classifier: Topic :: Software Development :: Libraries :: Python Modules
Requires-Python: <3.13,>=3.10
License-File: LICENSE.md
Requires-Dist: adlfs==2024.12.0
Requires-Dist: azure-common==1.1.28
Requires-Dist: azure-storage-blob==12.24.*
Requires-Dist: azure-storage-file-datalake==12.18.*
Requires-Dist: boto3==1.35.81
Requires-Dist: s3fs==2024.12.0
Requires-Dist: gcsfs==2024.12.*
Requires-Dist: fs_gcsfs==1.5.1
Requires-Dist: google-cloud-bigquery-storage==2.27.0
Requires-Dist: google-cloud-storage==2.19.0
Requires-Dist: pandas_gbq==0.26.*
Requires-Dist: mysql-connector-python==9.1.0
Requires-Dist: openpyxl==3.1.*
Requires-Dist: sqlparse==0.5.*
Requires-Dist: SQLAlchemy<3.0,>=2.0
Requires-Dist: pyodbc==5.2.0
Requires-Dist: pymysql==1.1.1
Requires-Dist: psycopg2==2.9.*
Requires-Dist: snowflake-sqlalchemy==1.7.7
Requires-Dist: snowflake-connector-python==3.18.0
Requires-Dist: uuid==1.30
Requires-Dist: delta-sharing==1.3.1
Requires-Dist: databricks-sdk==0.41.0
Requires-Dist: databricks-sql-connector[sqlalchemy]
Requires-Dist: ydata-profiling>4.16.0
Requires-Dist: visions[type_image_path]<0.8.0,>=0.7.5
Requires-Dist: ipywidgets<9.0.0,>=8.0.0
Requires-Dist: dacite>=1.8.0
Requires-Dist: datasketch==1.6.*
Requires-Dist: fuzzywuzzy==0.18.*
Requires-Dist: python-Levenshtein==0.27.*
Requires-Dist: miceforest>=5.6.3
Requires-Dist: pyod>=2.0.0
Requires-Dist: hdbscan==0.8.40
Requires-Dist: weasyprint<65,>=58.0
Requires-Dist: pdf_reports>=0.3.5
Requires-Dist: libsass>=0.22.0
Requires-Dist: ydata-datascience>=0.7.0
Requires-Dist: statsmodels==0.14.4
Requires-Dist: exrex==0.12.0
Requires-Dist: faker==33.3.1
Requires-Dist: dask==2024.12.1
Requires-Dist: distributed==2024.12.1
Requires-Dist: dask-gateway==2024.1.0
Requires-Dist: ydata-core>=0.7.0
Requires-Dist: ydata-datascience>=0.7.0
Requires-Dist: pandas<2.4
Requires-Dist: numpy<2.5.0,>=1.26.0
Requires-Dist: scipy>=1.9.0
Requires-Dist: scikit-learn==1.6.*
Requires-Dist: tqdm<4.65,>=4.48
Requires-Dist: typeguard<5
Requires-Dist: pydantic<3
Requires-Dist: dill==0.3.*
Requires-Dist: networkx>=3.0.0
Requires-Dist: seaborn==0.13.*
Requires-Dist: psutil==6.1.*
Requires-Dist: presidio_analyzer==2.2.*
Requires-Dist: pyarrow<19,>=16
Provides-Extra: text
Requires-Dist: tiktoken>=0.9.0; extra == "text"
Requires-Dist: tenacity>=9.0.0; extra == "text"
Requires-Dist: openai>=1.70.0; extra == "text"
Requires-Dist: anthropic>=0.49.0; extra == "text"
Requires-Dist: langchain_community; extra == "text"
Requires-Dist: langchain; extra == "text"
Provides-Extra: docx
Requires-Dist: langchain_community; extra == "docx"
Requires-Dist: langchain; extra == "docx"
Requires-Dist: unstructured[docx]; extra == "docx"
Requires-Dist: html-for-docx>=1.0.6; extra == "docx"
Requires-Dist: python-docx>=1.1.2; extra == "docx"
Dynamic: license-file
Dynamic: provides-extra
Dynamic: requires-dist
